{
  "compSpecs": [
    {
      "buildNumber": 1000,
      "componentCode": "c-springboot",
      "componentVersion": "0.0.1",
      "orderNumber": 0,
      "srmSpecCode": "k8s.euler.simple-web-8080",
      "srmSpecName": "单机"
    }
  ],
  "envCode": "euler-market",
  "offerId": "1",
  "productCode": "custom",
  "productInstanceAttrs": [
    {
      "attrId": "1d1b1ee4-8bce-4bc4-8353-d76b2c3b7eca",
      "attrKey": "cpu-request",
      "attrValue": "250",
      "componentCode": "c-springboot",
      "componentVersion": "0.0.1",
      "source": "1",
      "srmSpecCode": "k8s.euler.simple-web-8080",
      "srmSpecName": "单机"
    },
    {
      "attrId": "2da77b62-4bfb-4dcb-815f-c94744237c48",
      "attrKey": "image-pull-policy",
      "attrValue": "IfNotPresent",
      "componentCode": "c-springboot",
      "componentVersion": "0.0.1",
      "source": "1",
      "srmSpecCode": "k8s.euler.simple-web-8080",
      "srmSpecName": "单机"
    },
    {
      "attrId": "2ddb59ec-1d5e-4785-854f-aaebced41401",
      "attrKey": "db.user",
      "attrValue": "root",
      "componentCode": "c-springboot",
      "componentVersion": "0.0.1",
      "source": "2",
      "srmSpecCode": "k8s.euler.simple-web-8080",
      "srmSpecName": "单机"
    },
    {
      "attrId": "39ad152f-16ef-45c7-81d3-b5bc12fe8e68",
      "attrKey": "db.url",
      "attrValue": "jdbc:mysql://10.217.4.34:32788/test?autoReconnect=true&characterEncoding=UTF-8",
      "componentCode": "c-springboot",
      "componentVersion": "0.0.1",
      "source": "2",
      "srmSpecCode": "k8s.euler.simple-web-8080",
      "srmSpecName": "单机"
    },
    {
      "attrId": "94edff61-d401-4f47-82fe-48f540c5e00f",
      "attrKey": "db.password",
      "attrValue": "c_krit",
      "componentCode": "c-springboot",
      "componentVersion": "0.0.1",
      "source": "2",
      "srmSpecCode": "k8s.euler.simple-web-8080",
      "srmSpecName": "单机"
    },
    {
      "attrId": "a1f1f536-a966-46c7-b924-c302a359dc87",
      "attrKey": "cpu-limit",
      "attrValue": "500",
      "componentCode": "c-springboot",
      "componentVersion": "0.0.1",
      "source": "1",
      "srmSpecCode": "k8s.euler.simple-web-8080",
      "srmSpecName": "单机"
    }
  ],
  "productSpecId": "4bfddc9c-c10b-4354-8b1c-ccf76bae0f08",
  "productVersion": "0.1.0",
  "providerCode": "tenant-tianxh",
  "spmVersion": "0.1.0",
  "standardProductId": "bbc33ed5-2042-42e2-84b3-708de69f61b5",
  "tenantCode": "tenant-tianxh",
  "usedCount": 0
}